com_chery/chery_user_model_service/__init__.py
com_chery/chery_user_model_service/pom.py
com_chery/chery_user_model_service/user.py
com_chery/chery_user_model_service/user_service.py
com_chery_user_model_service-0.0.6.dist-info/METADATA
com_chery_user_model_service-0.0.6.dist-info/WHEEL
com_chery_user_model_service-0.0.6.dist-info/top_level.txt
com_chery_user_model_service-0.0.6.dist-info/RECORD
