Metadata-Version: 2.1
Name: com-chery-user-model-service
Version: 0.0.6
Summary: temp package, will be deleted later 2024-12-24
Home-page: UNKNOWN
License: UNKNOWN
Platform: UNKNOWN
Classifier: Programming Language :: Python :: 3
Classifier: Operating System :: OS Independent
Requires-Dist: requests
Requires-Dist: python-dotenv
